{
    "boost.color.any": "vilken färg som helst",
    "boost.color.black": "svart",
    "boost.color.blue": "blå",
    "boost.color.green": "grön",
    "boost.color.red": "röd",
    "boost.color.white": "vit",
    "boost.color.yellow": "gul",
    "boost.getMotorPosition": "motor [MOTOR_REPORTER_ID] position",
    "boost.getTiltAngle": "lutningsvinkel [TILT_DIRECTION]",
    "boost.motorDirection.backward": "andra hållet",
    "boost.motorDirection.forward": "detta hållet",
    "boost.motorDirection.reverse": "ändra riktning",
    "boost.motorOff": "vrid motor [MOTOR_ID] av",
    "boost.motorOn": "vrid motor [MOTOR_ID] på",
    "boost.motorOnFor": "vrid motor [MOTOR_ID] i [DURATION] sekunder",
    "boost.motorOnForRotation": "vrid motor [MOTOR_ID] i [ROTATION] rotationer",
    "boost.seeingColor": "ser [COLOR] kloss?",
    "boost.setLightHue": "sätt ljusets färg till [HUE]",
    "boost.setMotorDirection": "sätt motor [MOTOR_ID] riktning [MOTOR_DIRECTION]",
    "boost.setMotorPower": "sätt motor [MOTOR_ID] hastighet till [POWER] %",
    "boost.tiltDirection.any": "någon",
    "boost.tiltDirection.down": "ned",
    "boost.tiltDirection.left": "vänster",
    "boost.tiltDirection.right": "höger",
    "boost.tiltDirection.up": "upp",
    "boost.whenColor": "när [COLOR] kloss upptäcks",
    "boost.whenTilted": "om lutar [TILT_DIRECTION_ANY]",
    "ev3.beepNote": "spela ton [NOTE] i [TIME]sekunder",
    "ev3.buttonPressed": "knapp [PORT] nedtryckt?",
    "ev3.getBrightness": "ljusstyrka",
    "ev3.getDistance": "avstånd",
    "ev3.getMotorPosition": "motor [PORT] position",
    "ev3.motorSetPower": "motor [PORT] sätt kraft [POWER] %",
    "ev3.motorTurnClockwise": "motor [PORT] rotera medsols i [TIME] sekunder",
    "ev3.motorTurnCounterClockwise": "motor [PORT] rotera motsols i [TIME] sekunder",
    "ev3.whenBrightnessLessThan": "om ljusstyrka < [DISTANCE]",
    "ev3.whenButtonPressed": "när knapp [PORT] trycks ned",
    "ev3.whenDistanceLessThan": "när avstånd < [DISTANCE]",
    "gdxfor.getAcceleration": "acceleration [DIRECTION]",
    "gdxfor.getForce": "kraft",
    "gdxfor.getSpin": "rotationshastighet [DIRECTION]",
    "gdxfor.getTilt": "lutningsvinkel [TILT]",
    "gdxfor.isFreeFalling": "fritt fall?",
    "gdxfor.isTilted": "lutar [TILT]?",
    "gdxfor.pulled": "dragits",
    "gdxfor.pushed": "knuffad",
    "gdxfor.shaken": "skaka",
    "gdxfor.startedFalling": "börjar falla",
    "gdxfor.tiltDirectionMenu.any": "någon",
    "gdxfor.tiltDirectionMenu.back": "tillbaka",
    "gdxfor.tiltDirectionMenu.front": "översta",
    "gdxfor.tiltDirectionMenu.left": "vänster",
    "gdxfor.tiltDirectionMenu.right": "höger",
    "gdxfor.turnedFaceDown": "vände logotyp nedåt",
    "gdxfor.turnedFaceUp": "vände logotyp uppåt",
    "gdxfor.whenForcePushedOrPulled": "när kraftsensorn [PUSH_PULL]",
    "gdxfor.whenGesture": "om [GESTURE]",
    "gdxfor.whenTilted": "när lutar [TILT]",
    "makeymakey.downArrow": "nedåtpil",
    "makeymakey.downArrowShort": "ned",
    "makeymakey.leftArrow": "vänsterpil",
    "makeymakey.leftArrowShort": "vänster",
    "makeymakey.rightArrow": "högerpil",
    "makeymakey.rightArrowShort": "höger",
    "makeymakey.spaceKey": "mellanslag",
    "makeymakey.upArrow": "uppåtpil",
    "makeymakey.upArrowShort": "upp",
    "makeymakey.whenKeyPressed": "när [KEY] tangenten trycks ned",
    "makeymakey.whenKeysPressedInOrder": "när [SEQUENCE] trycks ned efter varandra",
    "microbit.buttonsMenu.any": "någon",
    "microbit.clearDisplay": "rensa skärmen",
    "microbit.defaultTextToDisplay": "Hej!",
    "microbit.displaySymbol": "visa [MATRIX]",
    "microbit.displayText": "visa text [TEXT]",
    "microbit.gesturesMenu.jumped": "hoppa",
    "microbit.gesturesMenu.moved": "rör sig",
    "microbit.gesturesMenu.shaken": "skaka",
    "microbit.isButtonPressed": "[BTN] knappen nedtryckt?",
    "microbit.isTilted": "luta [DIRECTION]?",
    "microbit.pinStateMenu.off": "av",
    "microbit.pinStateMenu.on": "på",
    "microbit.tiltAngle": "luta riktning [DIRECTION]",
    "microbit.tiltDirectionMenu.any": "någon",
    "microbit.tiltDirectionMenu.back": "tillbaka",
    "microbit.tiltDirectionMenu.front": "översta",
    "microbit.tiltDirectionMenu.left": "vänster",
    "microbit.tiltDirectionMenu.right": "höger",
    "microbit.whenButtonPressed": "om knapp [BTN] trycks ned",
    "microbit.whenGesture": "om [GESTURE]",
    "microbit.whenPinConnected": "När pin [PIN] är kopplad",
    "microbit.whenTilted": "om lutar [DIRECTION]",
    "matatabot.motionForwardStep": "move [STEP] forward",
    "matatabot.motionBackwardStep": "move [STEP] backward",
    "matatabot.motionStepMenu.step1": "1 step",
    "matatabot.motionStepMenu.step2": "2 steps",
    "matatabot.motionStepMenu.step3": "3 steps",
    "matatabot.motionStepMenu.step4": "4 steps",
    "matatabot.motionStepMenu.step5": "5 steps",
    "matatabot.motionStepMenu.step6": "6 steps",
    "matatabot.motionStepMenu.rollDice": "roll dice",
    "matatabot.motionTurnLeftAngle": "turn [ANGLE] left",
    "matatabot.motionTurnRightAngle": "turn [ANGLE] right",
    "matatabot.motionAngleMenu.degree30": "30°",
    "matatabot.motionAngleMenu.degree36": "36°",
    "matatabot.motionAngleMenu.degree45": "45°",
    "matatabot.motionAngleMenu.degree60": "60°",
    "matatabot.motionAngleMenu.degree72": "72°",
    "matatabot.motionAngleMenu.degree90": "90°",
    "matatabot.motionAngleMenu.degree108": "108°",
    "matatabot.motionAngleMenu.degree120": "120°",
    "matatabot.motionAngleMenu.degree135": "135°",
    "matatabot.motionAngleMenu.degree144": "144°",
    "matatabot.motionAngleMenu.degree150": "150°",
    "matatabot.motionAngleMenu.degree180": "180°",
    "matatabot.motionMoving": "move [POS] cm",
    "matatabot.motionWhirl": "rotate [ANGLE] degrees",
    "matatabot.motionWheelPower": "set left wheel [LEFT_DIR] speed [LEFT_GEAR], set right wheel [RIGHT_DIR] speed [RIGHT_GEAR]",
    "matatabot.motionTrendMenu.forward": "forward",
    "matatabot.motionTrendMenu.backward": "backward",
    "matatabot.motionGearMenu.gear1": "gear 1",
    "matatabot.motionGearMenu.gear2": "gear 2",
    "matatabot.motionGearMenu.gear3": "gear 3",
    "matatabot.motionGearMenu.gear4": "gear 4",
    "matatabot.motionGearMenu.gear5": "gear 5",
    "matatabot.motionGearMenu.gear6": "gear 6",
    "matatabot.motionGearMenu.stop": "stop",
    "matatabot.motionGearMenu.unchanged": "unchanged",
    "matatabot.motionGearMenu.rollDice": "roll dice",
    "matatabot.motionWheelSpeed": "set left motor speed [LEFT] cm/s, set right motor speed [RIGHT] cm/s",
    "matatabot.motionStopMoving": "[WHEEL] stop moving",
    "matatabot.motionWheelMenu.left": "left wheel",
    "matatabot.motionWheelMenu.right": "right wheel",
    "matatabot.motionWheelMenu.both": "both wheels",
    "matatabot.doDance": "perform [DANCE_INDEX] dance",
    "matatabot.danceIndexMenu.num1": "the 1st",
    "matatabot.danceIndexMenu.num2": "the 2nd",
    "matatabot.danceIndexMenu.num3": "the 3rd",
    "matatabot.danceIndexMenu.num4": "the 4th",
    "matatabot.danceIndexMenu.num5": "the 5th",
    "matatabot.danceIndexMenu.num6": "the 6th",
    "matatabot.danceIndexMenu.rollDice": "roll dice",
    "matatabot.doAction": "perform [ACTION_INDEX] action",
    "matatabot.actionIndexMenu.num1": "the 1st",
    "matatabot.actionIndexMenu.num2": "the 2nd",
    "matatabot.actionIndexMenu.num3": "the 3rd",
    "matatabot.actionIndexMenu.num4": "the 4th",
    "matatabot.actionIndexMenu.num5": "the 5th",
    "matatabot.actionIndexMenu.num6": "the 6th",
    "matatabot.actionIndexMenu.rollDice": "roll dice",
    "matatabot.soundAlto": "play alto [TONE] for [BEAT] beats",
    "matatabot.soundTreble": "play treble [TONE] for [BEAT] beats",
    "matatabot.soundBeat.oneFourth": "1/4",
    "matatabot.soundBeat.twoFourth": "2/4",
    "matatabot.soundBeat.threeFourth": "3/4",
    "matatabot.soundBeat.fourFourth": "4/4",
    "matatabot.soundBeat.fiveFourth": "5/4",
    "matatabot.soundBeat.sixFourth": "6/4",
    "matatabot.soundBeat.rollDice": "roll dice",
    "matatabot.soundTone.do": "do",
    "matatabot.soundTone.re": "re",
    "matatabot.soundTone.mi": "mi",
    "matatabot.soundTone.fa": "fa",
    "matatabot.soundTone.so": "so",
    "matatabot.soundTone.la": "la",
    "matatabot.soundTone.ti": "ti",
    "matatabot.soundMelody": "play [MELODY] melody",
    "matatabot.soundMelody.num1": "the 1st",
    "matatabot.soundMelody.num2": "the 2nd",
    "matatabot.soundMelody.num3": "the 3rd",
    "matatabot.soundMelody.num4": "the 4th",
    "matatabot.soundMelody.num5": "the 5th",
    "matatabot.soundMelody.num6": "the 6th",
    "matatabot.soundMelody.num7": "the 7th",
    "matatabot.soundMelody.num8": "the 8th",
    "matatabot.soundMelody.num9": "the 9th",
    "matatabot.soundMelody.num10": "the 10th",
    "matatabot.soundSong": "play [SONG] song",
    "matatabot.soundSong.num1": "the 1st",
    "matatabot.soundSong.num2": "the 2nd",
    "matatabot.soundSong.num3": "the 3rd",
    "matatabot.soundSong.num4": "the 4th",
    "matatabot.soundSong.num5": "the 5th",
    "matatabot.soundSong.num6": "the 6th",
    "matatabot.soundSong.rollDice": "roll dice",
    "matatabot.eyeLedSingleSet1": "set [SIDE] eye(s) to [COLOR_TYPE] and brightness is level [BRIGHTNESS_LEVEL]",
    "matatabot.looksSideMenu.left": "left",
    "matatabot.looksSideMenu.right": "right",
    "matatabot.looksSideMenu.all": "all",
    "matatabot.colorTypeMenu.white": "white",
    "matatabot.colorTypeMenu.red": "red",
    "matatabot.colorTypeMenu.yellow": "yellow",
    "matatabot.colorTypeMenu.green": "green",
    "matatabot.colorTypeMenu.blue": "blue",
    "matatabot.colorTypeMenu.purple": "purple",
    "matatabot.colorTypeMenu.black": "black",
    "matatabot.brightnessLevelMenu.lev1": "1",
    "matatabot.brightnessLevelMenu.lev2": "2",
    "matatabot.brightnessLevelMenu.lev3": "3",
    "matatabot.brightnessLevelMenu.lev4": "4",
    "matatabot.brightnessLevelMenu.lev5": "5",
    "matatabot.brightnessLevelMenu.lev6": "6",
    "matatabot.brightnessLevelMenu.rollDice": "roll dice",
    "matatabot.eyeLedSingleSet2": "set [SIDE] eye(s) to color [COLOR]",
    "matatabot.eyeLedSingleSet3": "set eye [LED_INDEX] red [RED_VALUE] green [GREEN_VALUE] blue [BLUE_VALUE]",
    "matatabot.eyeLedAllOff": "turn all eyes off",
    "matatacon.lightRingLedSingleSet1": "set [LED_INDEX] LED(s) to [COLOR_TYPE] and brightness is level [BRIGHTNESS_LEVEL]",
    "matatacon.ledRingIndexMenu.num1": "the 1st",
    "matatacon.ledRingIndexMenu.num2": "the 2nd",
    "matatacon.ledRingIndexMenu.num3": "the 3rd",
    "matatacon.ledRingIndexMenu.num4": "the 4th",
    "matatacon.ledRingIndexMenu.num5": "the 5th",
    "matatacon.ledRingIndexMenu.num6": "the 6th",
    "matatacon.ledRingIndexMenu.num7": "the 7th",
    "matatacon.ledRingIndexMenu.num8": "the 8th",
    "matatacon.ledRingIndexMenu.num9": "the 9th",
    "matatacon.ledRingIndexMenu.num10": "the 10th",
    "matatacon.ledRingIndexMenu.num11": "the 11th",
    "matatacon.ledRingIndexMenu.num12": "the 12th",
    "matatacon.ledRingIndexMenu.all": "all",
    "matatacon.colorTypeMenu.white": "white",
    "matatacon.colorTypeMenu.red": "red",
    "matatacon.colorTypeMenu.yellow": "yellow",
    "matatacon.colorTypeMenu.green": "green",
    "matatacon.colorTypeMenu.blue": "blue",
    "matatacon.colorTypeMenu.purple": "purple",
    "matatacon.colorTypeMenu.black": "black",
    "matatacon.brightnessLevelMenu.lev1": "1",
    "matatacon.brightnessLevelMenu.lev2": "2",
    "matatacon.brightnessLevelMenu.lev3": "3",
    "matatacon.brightnessLevelMenu.lev4": "4",
    "matatacon.brightnessLevelMenu.lev5": "5",
    "matatacon.brightnessLevelMenu.lev6": "6",
    "matatacon.brightnessLevelMenu.rollDice": "roll dice",
    "matatacon.lightRingLedSingleSet2": "set [LED_INDEX] LED(s) to color [COLOR_VALUE]",
    "matatacon.lightRingLedSingleSet3": "set LED [LED_INDEX] red [RED_VALUE] green [GREEN_VALUE] blue [BLUE_VALUE]",
    "matatacon.lightRingLedSingleSet4": "set led ring light [PANEL]",
    "matatacon.lightRingShowEffect": "LED ring light show [LIGHT_EFFECT]",
    "matatacon.lightEffectMenu.spoondrift": "spoondrift",
    "matatacon.lightEffectMenu.meteor": "meteor",
    "matatacon.lightEffectMenu.rainbow": "rainbow",
    "matatacon.lightEffectMenu.firefly": "firefly",
    "matatacon.lightEffectMenu.colorwipe": "colorwipe",
    "matatacon.lightEffectMenu.breathe": "breathe",
    "matatacon.lightRingAllLedOff": "turn all LEDs off",
    "matatacon.sendIRMessage": "send message [MESSAGE_INDEX]",
    "matatacon.waitIRMessage": "wait for message [MESSAGE_INDEX]",
    "matatacon.messageIndexMenu.msg1": "one",
    "matatacon.messageIndexMenu.msg2": "two",
    "matatacon.messageIndexMenu.msg3": "three",
    "matatacon.messageIndexMenu.msg4": "four",
    "matatacon.messageIndexMenu.msg5": "five",
    "matatacon.messageIndexMenu.msg6": "six",
    "matatacon.messageIndexMenu.rollDice": "roll dice",
    "matatacon.isButtonPressed": "button [BUTTON_KEY] pressed?",    "matatacon.buttonKeyMenu.play": "play",
    "matatacon.buttonKeyMenu.delete": "delete",
    "matatacon.buttonKeyMenu.music": "music",
    "matatacon.buttonKeyMenu.forward": "forward",
    "matatacon.buttonKeyMenu.backward": "backward",
    "matatacon.buttonKeyMenu.left": "left",
    "matatacon.buttonKeyMenu.right": "right",
    "matatacon.motionSensorStatus": "sensing [MOTION_STATUS]?",
    "matatacon.motinStatusMenu.shaken": "shaken",
    "matatacon.motinStatusMenu.up": "face up",
    "matatacon.motinStatusMenu.down": "face down",
    "matatacon.motinStatusMenu.left": "tilted left",
    "matatacon.motinStatusMenu.right": "tilted right",
    "matatacon.motinStatusMenu.front": "tilted down",
    "matatacon.motinStatusMenu.back": "tilted up",
    "matatacon.motinStatusMenu.freeFall": "free fall",
    "matatacon.recognizeColor": "detect color [COLOR_TYPE]?",
    "matatacon.isHearSomething": "hear sound?",
    "matatacon.isObstaclesAhead": "meet obstacle?",
    "matatacon.isBrightness": "detect brightness?",
    "matatacon.getPitchAngle": "pitch angle°",
    "matatacon.getRollAngle": "roll angle°",
    "matatacon.getYawAngle": "yaw angle°",
    "matatacon.getShakingStrength": "shaking intensity",
    "matatacon.getAmbientLightIntensity": "ambient light intensity",
    "matatacon.getRGBColor": "[COLOR_CHANNEL] color value",
    "matatacon.colorChannelMenu.red": "red",
    "matatacon.colorChannelMenu.green": "green",
    "matatacon.colorChannelMenu.blue": "blue",
    "matatacon.getAcceleration": "[AXIS_VALUE] acceleration",
    "matatacon.axisValueMenu.x": "x-axis",
    "matatacon.axisValueMenu.y": "y-axis",
    "matatacon.axisValueMenu.z": "z-axis",
    "matatacon.whenButtonPressed": "when button [BUTTON_KEY] pressed",
    "matatacon.whenAttitudeChangeTo": "when attitude [MOTION_STATUS]",
    "matatacon.whenHearSomething": "when hear sound",
    "music.categoryName": "Musik",
    "music.changeTempo": "ändra tempo med [TEMPO]",
    "music.drumBass": "(2) Bastrumma",
    "music.drumBongo": "(13) Bongo",
    "music.drumCabasa": "(15) Cabasa",
    "music.drumClaves": "(9) Claves",
    "music.drumClosedHiHat": "(6) Stängd Hi-Hat",
    "music.drumConga": "(14) Congas",
    "music.drumCowbell": "(11) Koskälla",
    "music.drumCrashCymbal": "(4) Crashcymbal",
    "music.drumCuica": "(18) Cuica",
    "music.drumGuiro": "(16) Guiro",
    "music.drumHandClap": "(8) Handklapp",
    "music.drumOpenHiHat": "(5) Öppen Hi-Hat",
    "music.drumSideStick": "(3) Kantslag",
    "music.drumSnare": "(1) Virveltrumma",
    "music.drumTambourine": "(7) Tamburin",
    "music.drumTriangle": "(12) Triangel",
    "music.drumVibraslap": "(17) Vibraslap",
    "music.drumWoodBlock": "(10) Träblock",
    "music.getTempo": "tempo",
    "music.instrumentBass": "(6) Bas",
    "music.instrumentBassoon": "(14) Fagott",
    "music.instrumentCello": "(8) Cello",
    "music.instrumentChoir": "(15) Kör",
    "music.instrumentClarinet": "(10) Klarinett",
    "music.instrumentElectricGuitar": "(5) Elgitarr",
    "music.instrumentElectricPiano": "(2) Elpiano",
    "music.instrumentFlute": "(12) Flöjt",
    "music.instrumentGuitar": "(4) Gitarr",
    "music.instrumentMarimba": "(19) Marimba",
    "music.instrumentMusicBox": "(17) Speldosa",
    "music.instrumentOrgan": "(3) Orgel",
    "music.instrumentPiano": "(1) Piano",
    "music.instrumentPizzicato": "(7) Pizzicato",
    "music.instrumentSaxophone": "(11) Saxofon",
    "music.instrumentSteelDrum": "(18) Steel Drum",
    "music.instrumentSynthLead": "(20) Synth Lead",
    "music.instrumentSynthPad": "(21) Synth Pad",
    "music.instrumentTrombone": "(9) Trombon",
    "music.instrumentVibraphone": "(16) Vibrafon",
    "music.instrumentWoodenFlute": "(13) Träflöjt",
    "music.midiPlayDrumForBeats": "spela trumma [DRUM]i [BEATS] takter",
    "music.midiSetInstrument": "sätt instrument till [INSTRUMENT]",
    "music.playDrumForBeats": "spela trumma [DRUM]i [BEATS] takter",
    "music.playNoteForBeats": "spela not [NOTE]i [BEATS]takter",
    "music.restForBeats": "pausa i [BEATS]takter",
    "music.setInstrument": "sätt instrument till [INSTRUMENT]",
    "music.setTempo": "sätt tempo till [TEMPO]",
    "pen.categoryName": "Penna",
    "pen.changeColorParam": "ändra pennans [COLOR_PARAM]med [VALUE]",
    "pen.changeHue": "ändra pennans färg med [HUE]",
    "pen.changeShade": "ändra pennans skugga med [SHADE]",
    "pen.changeSize": "ändra pennans storlek med [SIZE]",
    "pen.clear": "radera allt",
    "pen.colorMenu.brightness": "ljusstyrka",
    "pen.colorMenu.color": "färg",
    "pen.colorMenu.saturation": "mättnad",
    "pen.colorMenu.transparency": "genomskinlighet",
    "pen.penDown": "penna ned",
    "pen.penUp": "penna upp",
    "pen.setColor": "sätt pennans färg [COLOR]",
    "pen.setColorParam": "sätt penna [COLOR_PARAM]till [VALUE]",
    "pen.setHue": "sätt pennans färg till [HUE]",
    "pen.setShade": "sätt pennans skugga till [SHADE]",
    "pen.setSize": "sätt pennans storlek [SIZE]",
    "pen.stamp": "stämpla",
    "speech.defaultWhenIHearValue": "kör igång",
    "speech.extensionName": "Tal till text",
    "speech.listenAndWait": "lyssna och vänta",
    "speech.speechReporter": "tala",
    "speech.whenIHear": "när jag hör [PHRASE]",
    "text2speech.alto": "alt",
    "text2speech.categoryName": "Text till tal",
    "text2speech.defaultTextToSpeak": "hej",
    "text2speech.giant": "jätte",
    "text2speech.kitten": "kattunge",
    "text2speech.setLanguageBlock": "sätt språk till [LANGUAGE]",
    "text2speech.setVoiceBlock": "sätt röst till [VOICE]",
    "text2speech.speakAndWaitBlock": "säg [WORDS]",
    "text2speech.squeak": "pip",
    "text2speech.tenor": "tenor",
    "translate.categoryName": "Översätta",
    "translate.defaultTextToTranslate": "hej",
    "translate.translateBlock": "översätt [WORDS] till [LANGUAGE]",
    "translate.viewerLanguage": "språk",
    "videoSensing.categoryName": "Video - Känna av",
    "videoSensing.direction": "riktning",
    "videoSensing.motion": "rörelse",
    "videoSensing.off": "av",
    "videoSensing.on": "på",
    "videoSensing.onFlipped": "vid förändring",
    "videoSensing.setVideoTransparency": "sätt videotransparens till [TRANSPARENCY]",
    "videoSensing.sprite": "sprajt",
    "videoSensing.stage": "scen",
    "videoSensing.videoOn": "video [ATTRIBUTE]på [SUBJECT]",
    "videoSensing.videoToggle": "sätt video till [VIDEO_STATE]",
    "videoSensing.whenMotionGreaterThan": "när videorörelse > [REFERENCE]",
    "wedo2.getDistance": "avstånd",
    "wedo2.getTiltAngle": "lutningsvinkel [TILT_DIRECTION]",
    "wedo2.isTilted": "lutar [TILT_DIRECTION_ANY] ?",
    "wedo2.motorDirection.backward": "andra hållet",
    "wedo2.motorDirection.forward": "detta hållet",
    "wedo2.motorDirection.reverse": "ändra riktning",
    "wedo2.motorId.a": "motor A",
    "wedo2.motorId.all": "alla motorer",
    "wedo2.motorId.b": "motor B",
    "wedo2.motorId.default": "motor",
    "wedo2.motorOff": "stoppa [MOTOR_ID]",
    "wedo2.motorOn": "starta [MOTOR_ID]",
    "wedo2.motorOnFor": "starta [MOTOR_ID] i [DURATION] sekunder",
    "wedo2.playNoteFor": "spela ton [NOTE] i [DURATION] sekunder",
    "wedo2.setLightHue": "sätt ljusets färg till [HUE]",
    "wedo2.setMotorDirection": "sätt [MOTOR_ID] riktning till [MOTOR_DIRECTION]",
    "wedo2.startMotorPower": "sätt kraften på [MOTOR_ID] till [POWER]",
    "wedo2.tiltDirection.any": "någon",
    "wedo2.tiltDirection.down": "ned",
    "wedo2.tiltDirection.left": "vänster",
    "wedo2.tiltDirection.right": "höger",
    "wedo2.tiltDirection.up": "upp",
    "wedo2.whenDistance": "om avstånd [OP] [REFERENCE]",
    "wedo2.whenTilted": "om lutar [TILT_DIRECTION_ANY]"
}